nexio/__init__.py
nexio/exceptions.py
nexio/helpers/inbox.py
nexio/helpers/jobs.py
nexio/helpers/todoist.py
nexio/inbox.py
nexio/jobs.py
nexio/main.py
nexio/todoist.py
nexio/utils/postgres.py
nexio-0.1.3.dist-info/METADATA
nexio-0.1.3.dist-info/WHEEL
nexio-0.1.3.dist-info/entry_points.txt
nexio-0.1.3.dist-info/RECORD
